README.txt
setup.py
vincenty/__init__.py
vincenty.egg-info/PKG-INFO
vincenty.egg-info/SOURCES.txt
vincenty.egg-info/dependency_links.txt
vincenty.egg-info/top_level.txt