Metadata-Version: 1.1
Name: vincenty
Version: 0.1.1
Summary: Calculate the geographical distance between 2 points with extreme accuracy.
Home-page: https://github.com/maurycyp/vincenty
Author: Maurycy Pietrzak
Author-email: ['github.com@wayheavy.com']
License: Unlicense
Platform: UNKNOWN
Classifier: Development Status :: 4 - Beta
Classifier: Intended Audience :: Developers
Classifier: License :: Public Domain
Classifier: Operating System :: OS Independent
Classifier: Programming Language :: Python
Classifier: Programming Language :: Python :: 2
Classifier: Programming Language :: Python :: 3
Classifier: Topic :: Scientific/Engineering :: Mathematics
